{
  "company": {
    "name": "Malhotra Cables",
    "description": "Otomotiv, veri iletişimi ve yüksek gerilim kabloları üretiminde 20 yıllık mükemmellik.",
    "social": [
      { "key": "instagram", "url": "#" },
      { "key": "twitter",   "url": "#" },
      { "key": "facebook",  "url": "#" },
      { "key": "linkedin",  "url": "https://www.linkedin.com/company/malhotra-cables-pvt-ltd/?originalSubdomain=in" }
    ]
  },
  "quickLinks": [
    { "key": "MissionAndVision", "label": "Misyon ve Vizyon", "href": "/about/strategyMission&Vision" },
    { "key": "StandartsPolicy", "label": "Standart Politikası", "href": "/about/workingStandardsPolicy" },
    { "key": "Policy", "label": "Politika", "href": "/about/Policy" },
    { "key": "products", "label": "Ürünler", "href": "/products" },
    { "key": "suggestions", "label": "Öneri ve Şikayetler", "href": "/suggestions-and-complaints" }
  ],
  "productLinks": [
    { "key": "automotive",         "label": "Otomotiv Kabloları",         "href": "/products/automotive" },
    { "key": "data-communication", "label": "Veri İletişim Kabloları",     "href": "/products/data-communication" },
    { "key": "high-voltage",       "label": "Yüksek Gerilim Kabloları",    "href": "/products/high-voltage" },
    { "key": "custom",             "label": "Özel Çözümler",               "href": "/products/custom" }
  ],
  "contact": {
    "address": "123 Sanayi Bölgesi, Delhi NCR, Hindistan - 110001",
    "phone":   "+91 11 2345 6789",
    "email":   "info@malhotracables.com"
  }
}
